LICENSE
MANIFEST.in
README.rst
setup.py
django_baker/__init__.py
django_baker/admin.py
django_baker/bakery.py
django_baker/tests.py
django_baker.egg-info/PKG-INFO
django_baker.egg-info/SOURCES.txt
django_baker.egg-info/dependency_links.txt
django_baker.egg-info/top_level.txt
django_baker/management/__init__.py
django_baker/management/__pycache__/__init__.cpython-36.pyc
django_baker/management/commands/__init__.py
django_baker/management/commands/bake.py
django_baker/management/commands/__pycache__/__init__.cpython-36.pyc
django_baker/management/commands/__pycache__/bake.cpython-36.pyc
django_baker/templates/django_baker/__init__urls
django_baker/templates/django_baker/__init__views
django_baker/templates/django_baker/admin
django_baker/templates/django_baker/base.html
django_baker/templates/django_baker/create.html
django_baker/templates/django_baker/delete.html
django_baker/templates/django_baker/detail.html
django_baker/templates/django_baker/forms
django_baker/templates/django_baker/list.html
django_baker/templates/django_baker/update.html
django_baker/templates/django_baker/urls
django_baker/templates/django_baker/views