Metadata-Version: 1.1
Name: django-baker
Version: 0.22
Summary: Management command that generates views, forms, urls, admin, and templates for models
Home-page: https://github.com/krisfields/django-baker
Author: Kris Fields
Author-email: avalaunchit@gmail.com
License: BSD License
Keywords: generator generates
Platform: UNKNOWN
Classifier: Environment :: Web Environment
Classifier: Framework :: Django
Classifier: Intended Audience :: Developers
Classifier: License :: OSI Approved :: BSD License
Classifier: Operating System :: OS Independent
Classifier: Programming Language :: Python
Classifier: Programming Language :: Python :: 2.7
Classifier: Programming Language :: Python :: 3.6
Classifier: Topic :: Internet :: WWW/HTTP
Classifier: Topic :: Internet :: WWW/HTTP :: Dynamic Content
